<?xml version="1.0" encoding="UTF-8"?>
<!-- Generated by iWisdom 2.30 available from PowerSurgePub.com -->
<pw:wisdom xmlns:pw="http://www.powersurgepub.com/xml/wisdom">
  <pw:item>
    <pw:item-id>
      205
    </pw:item-id>
    <pw:category>
      <pw:category1>
        Software Development
      </pw:category1>
    </pw:category>
    <pw:title>
      No Silver Bullet
    </pw:title>
    <pw:file-name>
      no_silver_bullet
    </pw:file-name>
    <pw:body>
      <p>
        With the exception of a few hysterical CASE vendors and religious zealots, most software professionals would agree that there is no single silver bullet that will exorcise our software demons.
      </p>
    </pw:body>
    <pw:rating>
      Medium
    </pw:rating>
    <pw:author>
      <pw:name>
        Edward Yourdon
      </pw:name>
      <pw:last-name>
        Yourdon
      </pw:last-name>
      <pw:first-name>
        Edward
      </pw:first-name>
      <pw:file-name>
        edward_yourdon
      </pw:file-name>
      <pw:wikipedia-link>
        http://en.wikipedia.org/wiki/Edward_Yourdon
      </pw:wikipedia-link>
    </pw:author>
    <pw:source>
      <pw:type>
        Book
      </pw:type>
      <pw:title>
        Decline and Fall of the American Programmer
      </pw:title>
      <pw:identifier>
        013191958X
      </pw:identifier>
      <pw:rights>
        Copyright
      </pw:rights>
      <pw:year>
        1992
      </pw:year>
      <pw:owner>
        PTR Prentice-Hall, Inc.
      </pw:owner>
      <pw:file-name>
        decline_and_fall_of_the_american_programmer
      </pw:file-name>
    </pw:source>
    <pw:date-added>
      2006-11-30T14:29:31-08:00
    </pw:date-added>
  </pw:item>
</pw:wisdom>
